.gitignore
.gitmodules
.readthedocs.yaml
CMakeLists.txt
LICENSE
README.md
gcovr.cfg
pyproject.toml
requirements.txt
setup.py
.github/workflows/CI.yml
.github/workflows/python-publish.yml
.vscode/c_cpp_properties.json
cmake/CleanDirectoryList.cmake
cmake/CodeCoverage.cmake
cmake/CppcheckTargets.cmake
cmake/EnableProfiling.cmake
cmake/FindCVODE.cmake
cmake/FindFFTW.cmake
cmake/FindGDB.cmake
cmake/FindGSL.cmake
cmake/FindGitHub.cmake
cmake/FindITAPS.cmake
cmake/FindLAPACKLibs.cmake
cmake/FindLIS.cmake
cmake/FindMKL.cmake
cmake/FindMsysGit.cmake
cmake/FindNetCDF.cmake
cmake/FindOpenSG.cmake
cmake/FindOpenSGSupportlibs.cmake
cmake/FindShapelib.cmake
cmake/FindVRPN.cmake
cmake/Findcppcheck.cmake
cmake/Findcppcheck.cpp
cmake/Findquatlib.cmake
cmake/GetCPUDetails.cmake
cmake/GetGitRevisionDescription.cmake
cmake/GetGitRevisionDescription.cmake.in
cmake/LICENSE_1_0.txt
cmake/ListAllCMakeVariableValues.cmake
cmake/OptionRequires.cmake
cmake/PrintVariables.cmake
cmake/ProcessorCount.cmake
cmake/README.md
cmake/ResetConfigurations.cmake
cmake/SetDefaultBuildType.cmake
cmake/cotire-license
cmake/cotire.cmake
docs/make.bat
docs/requirements.txt
docs/source/api.rst
docs/source/conf.py
docs/source/env.md
docs/source/github_actions.md
docs/source/index.md
docs/source/pypi.md
docs/source/scbuild.md
docs/source/test.md
include/Ising.hpp
include/example.hpp
src/hybrid_example/CMakeLists.txt
src/hybrid_example/Ising_export.cpp
src/hybrid_example/__init__.py
src/hybrid_example/example_export.cpp
src/hybrid_example.egg-info/PKG-INFO
src/hybrid_example.egg-info/SOURCES.txt
src/hybrid_example.egg-info/dependency_links.txt
src/hybrid_example.egg-info/requires.txt
src/hybrid_example.egg-info/top_level.txt
test/CMakeLists.txt
test/__init__.py
test/test.cpp
test/test.py
test/lib/Catch2/.bazelrc
test/lib/Catch2/.clang-format
test/lib/Catch2/.gitattributes
test/lib/Catch2/.gitignore
test/lib/Catch2/BUILD.bazel
test/lib/Catch2/CMakeLists.txt
test/lib/Catch2/CMakePresets.json
test/lib/Catch2/CODE_OF_CONDUCT.md
test/lib/Catch2/Doxyfile
test/lib/Catch2/LICENSE.txt
test/lib/Catch2/README.md
test/lib/Catch2/SECURITY.md
test/lib/Catch2/WORKSPACE.bazel
test/lib/Catch2/appveyor.yml
test/lib/Catch2/codecov.yml
