Metadata-Version: 2.1
Name: hybrid-example
Version: 0.3.0
Summary: Tutorials about hybrid programming using C++ and Python
Home-page: https://github.com/yaozhenghangma/hybrid_programming/
Author: Yaozhenghang Ma
Author-email: Yaozhenghang.Ma@gmail.com
License: MIT
Project-URL: Bug Tracker, https://github.com/yaozhenghangma/hybrid_programming/issues/
Project-URL: Documentation, https://hybrid-programming.readthedocs.io/
Requires-Python: >=3.8
Provides-Extra: test
License-File: LICENSE
